{
  "accounts": {
    "audition": {
      "name": "$25,000 Audition Account",
      "initialValue": 25000,
      "currentValue": 25000,
      "status": "Audition Phase",
      "statusClass": "audition",
      "tradingSets": [
        {
          "setId": 1,
          "lotSize": 0.1,
          "maxLossPerTrade": 10,
          "trades": [],
          "totalProfitLoss": 0,
          "completed": false
        }
      ],
      "progressRules": {
        "progress": 50,
        "repeat": 0,
        "reduce": 0
      },
      "stats": {
        "totalPL": 0,
        "winRate": 0,
        "progressGoal": 0,
        "completedSets": 0
      }
    },
    "funded": {
      "name": "$1,000 Funded Account",
      "initialValue": 1000,
      "currentValue": 1000,
      "status": "Funded",
      "statusClass": "funded",
      "tradingSets": [
        {
          "setId": 1,
          "lotSize": 0.01,
          "maxLossPerTrade": 5,
          "trades": [],
          "totalProfitLoss": 0,
          "completed": false
        }
      ],
      "progressRules": {
        "progress": 25,
        "repeat": 0,
        "reduce": 0
      },
      "stats": {
        "totalPL": 0,
        "winRate": 0,
        "progressGoal": 0,
        "completedSets": 0
      }
    }
  }
}